model_card_generator/__init__.py
model_card_generator/__main__.py
model_card_generator/env.py
model_card_generator/json_writer.py
model_card_generator/model_data.py
model_card_generator/pdf_writer.py
model_card_generator/request.py
model_card_generator-0.2.0.dist-info/LICENSE
model_card_generator-0.2.0.dist-info/WHEEL
model_card_generator-0.2.0.dist-info/METADATA
model_card_generator-0.2.0.dist-info/RECORD
